qudata/__init__.py
qudata/cli.py
qudata/config.py
qudata/models.py
qudata/pipeline.py
qudata/analyze/__init__.py
qudata/analyze/analysis_engine.py
qudata/analyze/language_analyzer.py
qudata/analyze/quality_analyzer.py
qudata/analyze/sentiment_analyzer.py
qudata/analyze/text_analyzer.py
qudata/analyze/topic_modeler.py
qudata/annotate/__init__.py
qudata/annotate/metadata.py
qudata/annotate/ner.py
qudata/annotate/safety.py
qudata/annotate/taxonomy.py
qudata/annotate/topics.py
qudata/api/__init__.py
qudata/api/graphql_endpoint.py
qudata/api/rest_server.py
qudata/api/sdk_generator.py
qudata/api/webhook_manager.py
qudata/clean/__init__.py
qudata/clean/boilerplate.py
qudata/clean/comprehensive_preprocessor.py
qudata/clean/dedupe.py
qudata/clean/html_cleaner.py
qudata/clean/language.py
qudata/clean/normalize.py
qudata/clean/pipeline.py
qudata/clean/sanitize.py
qudata/clean/segment.py
qudata/clean/stopwords.py
qudata/clean/tokenization.py
qudata/database/__init__.py
qudata/database/backup.py
qudata/database/connector.py
qudata/database/incremental.py
qudata/database/nosql_extractor.py
qudata/database/partitioning.py
qudata/database/query_builder.py
qudata/database/schema_manager.py
qudata/database/sql_extractor.py
qudata/database/versioning.py
qudata/export/__init__.py
qudata/export/catalog.py
qudata/export/formats.py
qudata/export/llmbuilder.py
qudata/export/segmenter.py
qudata/ingest/__init__.py
qudata/ingest/api.py
qudata/ingest/db.py
qudata/ingest/detector.py
qudata/ingest/document.py
qudata/ingest/files.py
qudata/ingest/image.py
qudata/ingest/ocr.py
qudata/ingest/pdf.py
qudata/ingest/scraper.py
qudata/ingest/stream.py
qudata/ingest/structured.py
qudata/ingest/web.py
qudata/orchestrate/__init__.py
qudata/orchestrate/dependencies.py
qudata/orchestrate/models.py
qudata/orchestrate/orchestrator.py
qudata/orchestrate/retry.py
qudata/orchestrate/runner.py
qudata/orchestrate/scheduler.py
qudata/pack/__init__.py
qudata/pack/chatml.py
qudata/pack/jsonl.py
qudata/pack/plain.py
qudata-1.0.0.dist-info/METADATA
qudata-1.0.0.dist-info/WHEEL
qudata-1.0.0.dist-info/entry_points.txt
qudata-1.0.0.dist-info/top_level.txt
qudata-1.0.0.dist-info/RECORD
