Metadata-Version: 2.4
Name: qudata
Version: 1.0.0
Summary: Data processing pipeline for LLM training datasets
Author: Qub△se Team
License-Expression: MIT
Project-URL: Homepage, https://github.com/qubasehq/qudata
Project-URL: Repository, https://github.com/qubasehq/qudata
Project-URL: Issues, https://github.com/qubasehq/qudata/issues
Classifier: Development Status :: 4 - Beta
Classifier: Intended Audience :: Developers
Classifier: Programming Language :: Python :: 3
Classifier: Programming Language :: Python :: 3.8
Classifier: Programming Language :: Python :: 3.9
Classifier: Programming Language :: Python :: 3.10
Classifier: Programming Language :: Python :: 3.11
Requires-Python: >=3.8
Requires-Dist: pydantic>=2.0.0
Requires-Dist: pyyaml>=6.0
Requires-Dist: click>=8.0.0
Requires-Dist: rich>=13.0.0
Requires-Dist: pandas>=2.0.0
Requires-Dist: numpy>=1.24.0
Requires-Dist: beautifulsoup4>=4.12.0
Requires-Dist: requests>=2.31.0
Requires-Dist: pdfplumber>=0.10.0
Requires-Dist: python-docx>=0.8.11
Requires-Dist: nltk>=3.8.0
Requires-Dist: spacy>=3.6.0
Requires-Dist: langdetect>=1.0.9
Requires-Dist: chardet>=5.0.0
Requires-Dist: pytesseract>=0.3.10
Requires-Dist: opencv-python>=4.8.0
Requires-Dist: Pillow>=10.0.0
Requires-Dist: feedparser>=6.0.10
Requires-Dist: kafka-python>=2.0.2
Requires-Dist: plotly>=5.15.0
Requires-Dist: streamlit>=1.25.0
Requires-Dist: jinja2>=3.1.0
Requires-Dist: reportlab>=4.0.0
Requires-Dist: croniter>=1.4.0
Requires-Dist: PyMuPDF>=1.24.0
Requires-Dist: scikit-learn>=1.3.0
Requires-Dist: bertopic>=0.15.0
Requires-Dist: transformers>=4.30.0
Requires-Dist: fastapi>=0.110.0
Requires-Dist: psutil>=5.9.0
Requires-Dist: uvicorn[standard]>=0.23.0
Requires-Dist: gunicorn>=21.2.0
Provides-Extra: dev
Requires-Dist: pytest>=7.4.0; extra == "dev"
Requires-Dist: black>=23.7.0; extra == "dev"
Requires-Dist: flake8>=6.0.0; extra == "dev"
Requires-Dist: mypy>=1.5.0; extra == "dev"
Provides-Extra: web
Requires-Dist: scrapy>=2.10.0; extra == "web"
Requires-Dist: selenium>=4.10.0; extra == "web"
